Workbook

Sheet 封面
B2: 星座能源公司（NASDAQ: CEG）
B3: 股票研究报告 — 深度覆盖初报
B4: 财务模型 — 收入、利润表、现金流量表、资产负债表、情景分析、DCF估值
B7: 发布日期 | C7: 2026年6月17日
B8: 股票代码 | C8: CEG（纳斯达克）
B9: 行业 | C9: 公用事业 / 独立发电商（IPP）
B10: 总部 | C10: 美国马里兰州巴尔的摩市
B12: 当前总市值（参考价$220） | C12: ~$695亿
B13: 2025A总收入 | C13: $253亿
B14: 2026E调整后EPS | C14: $11.74（管理层指引$11.00–$12.00）
B15: 核能装机容量 | C15: 22.6 GW（美国最大，远超同业）
B16: 总装机容量（含卡尔派恩） | C16: ~55 GW
B18: 目标股价（基准情景） | C18: $255（较$220 +16%）
B19: 目标股价（乐观情景） | C19: $340（较$220 +55%）
B20: 估值方法 | C20: DCF（WACC 7.975%，g=3.0%）+ EV/EBITDA（15.0x）
B22: 核心投资主题
B23: 1. 美国最大核电运营商，护城河难以复制
B24: 2. AI数据中心爆发式电力需求首选清洁能源合作伙伴
B25: 3. 微软（835 MW）、Meta（1,121 MW）20年长期PPA锁定
B26: 4. IRA第45U条核能PTC（最高$15/MWh）保障盈利底部
B27: 5. 卡尔派恩收购后成全球最大私营发电商，规模协同显著
B29: 主要风险
B30: 1. 卡尔派恩整合执行风险（杠杆率偏高）
B31: 2. 第45U条核能PTC政策变动风险
B32: 3. FERC市场规则变化（PJM容量市场）
B33: 4. 克兰清洁能源中心（三里岛）重启延迟风险
B37: 免责声明：本模型基于公开信息构建，仅供研究参考，不构成投资建议。投资有风险，请独立判断。

Sheet 收入模型
A1: 星座能源公司（CEG）—— 收入模型（百万美元）
A2: 说明：蓝色 = 手工输入；黑色 = 公式；绿色 = 跨表链接
A3: 指标 | B3: 2022A | C3: 2023A | D3: 2024A | E3: 2025A | F3: 2026E | G3: 2027E | H3: 2028E | I3: 2029E
A4: ▌ 发电量（太瓦时，TWh）
A5: 核能发电量（TWh） | B5: 170.5 | C5: 172.3 | D5: 175.1 | E5: 176.8 | F5: 178 | G5: 186 | H5: 190 | I5: 192
A6: 天然气发电量（TWh） | B6: 0 | C6: 0 | D6: 0 | E6: 0 | F6: 142 | G6: 148 | H6: 152 | I6: 155
A7: 可再生能源发电量（TWh） | B7: 14.2 | C7: 15 | D7: 15.8 | E7: 16.3 | F7: 22.5 | G7: 23.5 | H7: 24 | I7: 24.5
A8: 合计发电量（TWh） | B8: =B5+B6+B7 | C8: =C5+C6+C7 | D8: =D5+D6+D7 | E8: =E5+E6+E7 | F8: =F5+F6+F7 | G8: =G5+G6+G7 | H8: =H5+H6+H7 | I8: =I5+I6+I7
A10: ▌ 实现价格（美元/兆瓦时，$/MWh）
A11: 核能实现价格（$/MWh） | B11: 42.5 | C11: 44.8 | D11: 47.2 | E11: 52.6 | F11: 56 | G11: 58 | H11: 60 | I11: 62
A12: 天然气实现价格（$/MWh） | B12: 0 | C12: 0 | D12: 0 | E12: 0 | F12: 48 | G12: 50 | H12: 52 | I12: 53
A13: 可再生能源实现价格（$/MWh） | B13: 38 | C13: 39.5 | D13: 41 | E13: 43.5 | F13: 45 | G13: 46 | H13: 47 | I13: 48
A15: ▌ 收入分部（百万美元）
A16: 核能发电收入 | B16: =B5*B11/1000 | C16: =C5*C11/1000 | D16: =D5*D11/1000 | E16: =E5*E11/1000 | F16: =F5*F11/1000 | G16: =G5*G11/1000 | H16: =H5*H11/1000 | I16: =I5*I11/1000
A17: 天然气发电收入 | B17: =B6*B12/1000 | C17: =C6*C12/1000 | D17: =D6*D12/1000 | E17: =E6*E12/1000 | F17: =F6*F12/1000 | G17: =G6*G12/1000 | H17: =H6*H12/1000 | I17: =I6*I12/1000
A18: 可再生能源收入 | B18: =B7*B13/1000 | C18: =C7*C13/1000 | D18: =D7*D13/1000 | E18: =E7*E13/1000 | F18: =F7*F13/1000 | G18: =G7*G13/1000 | H18: =H7*H13/1000 | I18: =I7*I13/1000
A19: 零售电力供应收入 | B19: 5820 | C19: 6210 | D19: 6850 | E19: 7320 | F19: 10500 | G19: 11000 | H19: 11500 | I19: 12000
A20: 其他收入 | B20: 320 | C20: 355 | D20: 390 | E20: 430 | F20: 680 | G20: 700 | H20: 720 | I20: 750
A21: 合计收入 | B21: =B16+B17+B18+B19+B20 | C21: =C16+C17+C18+C19+C20 | D21: =D16+D17+D18+D19+D20 | E21: =E16+E17+E18+E19+E20 | F21: =F16+F17+F18+F19+F20 | G21: =G16+G17+G18+G19+G20 | H21: =H16+H17+H18+H19+H20 | I21: =I16+I17+I18+I19+I20
A23: ▌ 同比增长率
A24: 收入增速（同比） | B24: — | C24: =C21/B21-1 | D24: =D21/C21-1 | E24: =E21/D21-1 | F24: =F21/E21-1 | G24: =G21/F21-1 | H24: =H21/G21-1 | I24: =I21/H21-1

Sheet 利润表
A1: 星座能源公司（CEG）—— 综合损益表（百万美元）
A2: 说明：蓝色 = 手工输入；黑色 = 公式；绿色 = 跨表链接
A3: 指标 | B3: 2022A | C3: 2023A | D3: 2024A | E3: 2025A | F3: 2026E | G3: 2027E | H3: 2028E | I3: 2029E
A4: ▌ 收入
A5: 总收入 | B5: ='收入模型'!B21 | C5: ='收入模型'!C21 | D5: ='收入模型'!D21 | E5: ='收入模型'!E21 | F5: ='收入模型'!F21 | G5: ='收入模型'!G21 | H5: ='收入模型'!H21 | I5: ='收入模型'!I21
A7: ▌ 运营成本
A8: 核燃料成本 | B8: =B5*0.062 | C8: =C5*0.06 | D8: =D5*0.058 | E8: =E5*0.055 | F8: =F5*0.053 | G8: =G5*0.052 | H8: =H5*0.051 | I8: =I5*0.05
A9: 运营与维护费用（O&M） | B9: 3500 | C9: 3620 | D9: 3750 | E9: 3900 | F9: 5800 | G9: 6000 | H9: 6200 | I9: 6400
A10: 折旧与摊销（D&A） | B10: 870 | C10: 920 | D10: 980 | E10: 1050 | F10: 1680 | G10: 1750 | H10: 1800 | I10: 1850
A11: 销售、一般及行政费用（SG&A） | B11: =B5*0.048 | C11: =C5*0.046 | D11: =D5*0.044 | E11: =E5*0.043 | F11: =F5*0.042 | G11: =G5*0.041 | H11: =H5*0.04 | I11: =I5*0.039
A12: 其他运营费用 | B12: 420 | C12: 395 | D12: 380 | E12: 370 | F12: 620 | G12: 600 | H12: 580 | I12: 560
A13: 合计运营成本 | B13: =B8+B9+B10+B11+B12 | C13: =C8+C9+C10+C11+C12 | D13: =D8+D9+D10+D11+D12 | E13: =E8+E9+E10+E11+E12 | F13: =F8+F9+F10+F11+F12 | G13: =G8+G9+G10+G11+G12 | H13: =H8+H9+H10+H11+H12 | I13: =I8+I9+I10+I11+I12
A15: ▌ 运营利润（EBIT）
A16: 运营利润（EBIT） | B16: =B5-B13 | C16: =C5-C13 | D16: =D5-D13 | E16: =E5-E13 | F16: =F5-F13 | G16: =G5-G13 | H16: =H5-H13 | I16: =I5-I13
A17: EBIT利润率 | B17: =B16/B5 | C17: =C16/C5 | D17: =D16/D5 | E17: =E16/E5 | F17: =F16/F5 | G17: =G16/G5 | H17: =H16/H5 | I17: =I16/I5
A19: ▌ EBITDA
A20: EBITDA | B20: =B16+B10 | C20: =C16+C10 | D20: =D16+D10 | E20: =E16+E10 | F20: =F16+F10 | G20: =G16+G10 | H20: =H16+H10 | I20: =I16+I10
A21: EBITDA利润率 | B21: =B20/B5 | C21: =C20/C5 | D21: =D20/D5 | E21: =E20/E5 | F21: =F20/F5 | G21: =G20/G5 | H21: =H20/H5 | I21: =I20/I5
A23: ▌ 税前利润（EBT）
A24: 利息及其他费用（净额） | B24: 310 | C24: 340 | D24: 360 | E24: 375 | F24: 820 | G24: 780 | H24: 750 | I24: 720
A25: 税前利润（EBT） | B25: =B16-B24 | C25: =C16-C24 | D25: =D16-D24 | E25: =E16-E24 | F25: =F16-F24 | G25: =G16-G24 | H25: =H16-H24 | I25: =I16-I24
A27: ▌ 净利润
A28: 所得税费用 | B28: =MAX(B25*0.22,0) | C28: =MAX(C25*0.21,0) | D28: =MAX(D25*0.2,0) | E28: =MAX(E25*0.19,0) | F28: =MAX(F25*0.21,0) | G28: =MAX(G25*0.21,0) | H28: =MAX(H25*0.21,0) | I28: =MAX(I25*0.21,0)
A29: 净利润 | B29: =B25-B28 | C29: =C25-C28 | D29: =D25-D28 | E29: =E25-E28 | F29: =F25-F28 | G29: =G25-G28 | H29: =H25-H28 | I29: =I25-I28
A31: ▌ 每股收益（EPS）
A32: 加权平均股数（百万股，稀释后） | B32: 327 | C32: 321.5 | D32: 318 | E32: 315 | F32: 314 | G32: 312 | H32: 310 | I32: 308
A33: 每股收益（GAAP） | B33: =B29/B32 | C33: =C29/C32 | D33: =D29/D32 | E33: =E29/E32 | F33: =F29/F32 | G33: =G29/G32 | H33: =H29/H32 | I33: =I29/I32
A34: 调整后每股收益（非GAAP） | B34: 4.85 | C34: 6.53 | D34: 8 | E34: 9.39 | F34: 11.74 | G34: 13.2 | H34: 14.8 | I34: 16.5
A35: （调整后EPS排除资产减值、重组费用及核燃料套保损益）

Sheet 现金流量表
A1: 星座能源公司（CEG）—— 现金流量表（百万美元）
A2: 说明：蓝色 = 手工输入；黑色 = 公式；绿色 = 跨表链接
A3: 指标 | B3: 2022A | C3: 2023A | D3: 2024A | E3: 2025A | F3: 2026E | G3: 2027E | H3: 2028E | I3: 2029E
A4: ▌ 经营活动现金流
A5: 净利润 | B5: ='利润表'!B29 | C5: ='利润表'!C29 | D5: ='利润表'!D29 | E5: ='利润表'!E29 | F5: ='利润表'!F29 | G5: ='利润表'!G29 | H5: ='利润表'!H29 | I5: ='利润表'!I29
A6: 加：折旧与摊销（D&A） | B6: ='利润表'!B10 | C6: ='利润表'!C10 | D6: ='利润表'!D10 | E6: ='利润表'!E10 | F6: ='利润表'!F10 | G6: ='利润表'!G10 | H6: ='利润表'!H10 | I6: ='利润表'!I10
A7: 营运资本变动（净额） | B7: -180 | C7: -210 | D7: -195 | E7: -220 | F7: -380 | G7: -320 | H7: -300 | I7: -280
A8: 递延所得税 | B8: 120 | C8: 135 | D8: 145 | E8: 160 | F8: 250 | G8: 240 | H8: 230 | I8: 220
A9: 其他非现金项目及调整 | B9: 85 | C9: 92 | D9: 78 | E9: 110 | F9: 160 | G9: 150 | H9: 140 | I9: 135
A10: 经营活动产生的现金流量净额 | B10: =B5+B6+B7+B8+B9 | C10: =C5+C6+C7+C8+C9 | D10: =D5+D6+D7+D8+D9 | E10: =E5+E6+E7+E8+E9 | F10: =F5+F6+F7+F8+F9 | G10: =G5+G6+G7+G8+G9 | H10: =H5+H6+H7+H8+H9 | I10: =I5+I6+I7+I8+I9
A12: ▌ 投资活动现金流
A13: 资本支出（CapEx） | B13: -1250 | C13: -1380 | D13: -1520 | E13: -1680 | F13: -3200 | G13: -2800 | H13: -2600 | I13: -2400
A14: 核电功率提升投资 | B14: 0 | C14: -85 | D14: -120 | E14: -180 | F14: -450 | G14: -380 | H14: -300 | I14: -250
A15: 收购卡尔派恩（净现金） | B15: 0 | C15: 0 | D15: 0 | E15: 0 | F15: -16400 | G15: 0 | H15: 0 | I15: 0
A16: 资产出售及其他投资 | B16: 0 | C16: 180 | D16: 95 | E16: 120 | F16: 350 | G16: 200 | H16: 150 | I16: 120
A17: 投资活动产生的现金流量净额 | B17: =B13+B14+B15+B16 | C17: =C13+C14+C15+C16 | D17: =D13+D14+D15+D16 | E17: =E13+E14+E15+E16 | F17: =F13+F14+F15+F16 | G17: =G13+G14+G15+G16 | H17: =H13+H14+H15+H16 | I17: =I13+I14+I15+I16
A19: ▌ 筹资活动现金流
A20: 债务发行（净额） | B20: 1200 | C20: 800 | D20: 500 | E20: 2500 | F20: 18000 | G20: -1500 | H20: -1500 | I20: -1500
A21: 股息支付 | B21: -320 | C21: -345 | D21: -370 | E21: -400 | F21: -480 | G21: -520 | H21: -560 | I21: -600
A22: 股票回购 | B22: -580 | C22: -720 | D22: -850 | E22: -900 | F22: -500 | G22: -600 | H22: -700 | I22: -800
A23: 其他筹资活动 | B23: -45 | C23: -38 | D23: -52 | E23: -60 | F23: -95 | G23: -80 | H23: -75 | I23: -70
A24: 筹资活动产生的现金流量净额 | B24: =B20+B21+B22+B23 | C24: =C20+C21+C22+C23 | D24: =D20+D21+D22+D23 | E24: =E20+E21+E22+E23 | F24: =F20+F21+F22+F23 | G24: =G20+G21+G22+G23 | H24: =H20+H21+H22+H23 | I24: =I20+I21+I22+I23
A26: ▌ 现金及现金等价物变动
A27: 现金净变动 | B27: =B10+B17+B24 | C27: =C10+C17+C24 | D27: =D10+D17+D24 | E27: =E10+E17+E24 | F27: =F10+F17+F24 | G27: =G10+G17+G24 | H27: =H10+H17+H24 | I27: =I10+I17+I24
A28: 期初现金余额 | B28: 1420 | C28: 2185 | D28: 2640 | E28: 2918 | F28: 3100 | G28: 1825 | H28: 1965 | I28: 2130
A29: 期末现金余额 | B29: =B28+B27 | C29: =C28+C27 | D29: =D28+D27 | E29: =E28+E27 | F29: =F28+F27 | G29: =G28+G27 | H29: =H28+H27 | I29: =I28+I27
A31: ▌ 自由现金流（FCF）
A32: 自由现金流（FCF）= 经营活动现金 + CapEx | B32: =B10+B13 | C32: =C10+C13 | D32: =D10+D13 | E32: =E10+E13 | F32: =F10+F13 | G32: =G10+G13 | H32: =H10+H13 | I32: =I10+I13
A33: FCF转换率（FCF/净利润） | B33: =IF(B5<>0,B32/B5,0) | C33: =IF(C5<>0,C32/C5,0) | D33: =IF(D5<>0,D32/D5,0) | E33: =IF(E5<>0,E32/E5,0) | F33: =IF(F5<>0,F32/F5,0) | G33: =IF(G5<>0,G32/G5,0) | H33: =IF(H5<>0,H32/H5,0) | I33: =IF(I5<>0,I32/I5,0)
A34: 每股自由现金流 | B34: =IF('利润表'!B32<>0,B32/'利润表'!B32,0) | C34: =IF('利润表'!C32<>0,C32/'利润表'!C32,0) | D34: =IF('利润表'!D32<>0,D32/'利润表'!D32,0) | E34: =IF('利润表'!E32<>0,E32/'利润表'!E32,0) | F34: =IF('利润表'!F32<>0,F32/'利润表'!F32,0) | G34: =IF('利润表'!G32<>0,G32/'利润表'!G32,0) | H34: =IF('利润表'!H32<>0,H32/'利润表'!H32,0) | I34: =IF('利润表'!I32<>0,I32/'利润表'!I32,0)

Sheet 资产负债表
A1: 星座能源公司（CEG）—— 资产负债表（百万美元）
A2: 说明：蓝色 = 手工输入；黑色 = 公式；绿色 = 跨表链接
A3: 指标 | B3: 2022A | C3: 2023A | D3: 2024A | E3: 2025A | F3: 2026E | G3: 2027E | H3: 2028E | I3: 2029E
A4: ▌ 流动资产
A5: 现金及现金等价物 | B5: ='现金流量表'!B29 | C5: ='现金流量表'!C29 | D5: ='现金流量表'!D29 | E5: ='现金流量表'!E29 | F5: ='现金流量表'!F29 | G5: ='现金流量表'!G29 | H5: ='现金流量表'!H29 | I5: ='现金流量表'!I29
A6: 应收账款（净额） | B6: 1820 | C6: 1950 | D6: 2100 | E6: 2280 | F6: 3500 | G6: 3650 | H6: 3800 | I6: 3950
A7: 存货（核燃料等） | B7: 380 | C7: 410 | D7: 435 | E7: 465 | F7: 720 | G7: 750 | H7: 770 | I7: 790
A8: 其他流动资产 | B8: 920 | C8: 980 | D8: 1040 | E8: 1120 | F8: 1750 | G8: 1800 | H8: 1850 | I8: 1900
A9: 流动资产合计 | B9: =B5+B6+B7+B8 | C9: =C5+C6+C7+C8 | D9: =D5+D6+D7+D8 | E9: =E5+E6+E7+E8 | F9: =F5+F6+F7+F8 | G9: =G5+G6+G7+G8 | H9: =H5+H6+H7+H8 | I9: =I5+I6+I7+I8
A11: ▌ 非流动资产
A12: 固定资产（净额，PP&E） | B12: 15800 | C12: 16500 | D12: 17200 | E12: 18100 | F12: 46500 | G12: 47800 | H12: 48500 | I12: 49000
A13: 商誉 | B13: 1240 | C13: 1240 | D13: 1240 | E13: 1240 | F13: 8500 | G13: 8500 | H13: 8500 | I13: 8500
A14: 无形资产（净额） | B14: 385 | C14: 360 | D14: 335 | E14: 310 | F14: 2800 | G14: 2600 | H14: 2400 | I14: 2200
A15: 核退役信托基金 | B15: 2580 | C15: 2750 | D15: 2920 | E15: 3050 | F15: 3200 | G15: 3350 | H15: 3500 | I15: 3650
A16: 其他非流动资产 | B16: 1020 | C16: 1080 | D16: 1140 | E16: 1230 | F16: 2200 | G16: 2150 | H16: 2100 | I16: 2050
A17: 非流动资产合计 | B17: =B12+B13+B14+B15+B16 | C17: =C12+C13+C14+C15+C16 | D17: =D12+D13+D14+D15+D16 | E17: =E12+E13+E14+E15+E16 | F17: =F12+F13+F14+F15+F16 | G17: =G12+G13+G14+G15+G16 | H17: =H12+H13+H14+H15+H16 | I17: =I12+I13+I14+I15+I16
A19: 资产总计 | B19: =B9+B17 | C19: =C9+C17 | D19: =D9+D17 | E19: =E9+E17 | F19: =F9+F17 | G19: =G9+G17 | H19: =H9+H17 | I19: =I9+I17
A21: ▌ 流动负债
A22: 应付账款 | B22: 1240 | C22: 1320 | D22: 1410 | E22: 1520 | F22: 2400 | G22: 2500 | H22: 2600 | I22: 2700
A23: 短期债务及一年内到期长期债务 | B23: 420 | C23: 650 | D23: 480 | E23: 500 | F23: 1200 | G23: 1200 | H23: 1200 | I23: 1200
A24: 应计负债 | B24: 985 | C24: 1050 | D24: 1120 | E24: 1210 | F24: 1900 | G24: 1950 | H24: 2000 | I24: 2050
A25: 其他流动负债 | B25: 680 | C25: 720 | D25: 760 | E25: 810 | F25: 1300 | G25: 1350 | H25: 1400 | I25: 1450
A26: 流动负债合计 | B26: =B22+B23+B24+B25 | C26: =C22+C23+C24+C25 | D26: =D22+D23+D24+D25 | E26: =E22+E23+E24+E25 | F26: =F22+F23+F24+F25 | G26: =G22+G23+G24+G25 | H26: =H22+H23+H24+H25 | I26: =I22+I23+I24+I25
A28: ▌ 非流动负债
A29: 长期债务 | B29: 7850 | C29: 8100 | D29: 8350 | E29: 8600 | F29: 23500 | G29: 22000 | H29: 20500 | I29: 19000
A30: 递延所得税负债 | B30: 1420 | C30: 1510 | D30: 1620 | E30: 1750 | F30: 2800 | G30: 2750 | H30: 2700 | I30: 2650
A31: 核退役义务（ARO） | B31: 3180 | C31: 3320 | D31: 3480 | E31: 3650 | F31: 4200 | G31: 4350 | H31: 4500 | I31: 4650
A32: 其他非流动负债 | B32: 850 | C32: 895 | D32: 940 | E32: 1000 | F32: 1600 | G32: 1580 | H32: 1560 | I32: 1540
A33: 非流动负债合计 | B33: =B29+B30+B31+B32 | C33: =C29+C30+C31+C32 | D33: =D29+D30+D31+D32 | E33: =E29+E30+E31+E32 | F33: =F29+F30+F31+F32 | G33: =G29+G30+G31+G32 | H33: =H29+H30+H31+H32 | I33: =I29+I30+I31+I32
A35: 负债总计 | B35: =B26+B33 | C35: =C26+C33 | D35: =D26+D33 | E35: =E26+E33 | F35: =F26+F33 | G35: =G26+G33 | H35: =H26+H33 | I35: =I26+I33
A37: ▌ 股东权益
A38: 普通股及资本公积 | B38: 3250 | C38: 3250 | D38: 3250 | E38: 3250 | F38: 3250 | G38: 3250 | H38: 3250 | I38: 3250
A39: 留存收益 | B39: 2180 | C39: 2950 | D39: 3720 | E39: 4560 | F39: 4980 | G39: 5620 | H39: 6380 | I39: 7240
A40: 其他综合收益（损失） | B40: -420 | C40: -380 | D40: -350 | E40: -310 | F40: -380 | G40: -360 | H40: -340 | I40: -320
A41: 库存股（成本法） | B41: -3680 | C41: -4400 | D41: -5250 | E41: -6150 | F41: -6650 | G41: -7250 | H41: -7950 | I41: -8750
A42: 股东权益合计 | B42: =B38+B39+B40+B41 | C42: =C38+C39+C40+C41 | D42: =D38+D39+D40+D41 | E42: =E38+E39+E40+E41 | F42: =F38+F39+F40+F41 | G42: =G38+G39+G40+G41 | H42: =H38+H39+H40+H41 | I42: =I38+I39+I40+I41
A44: 负债及股东权益总计 | B44: =B35+B42 | C44: =C35+C42 | D44: =D35+D42 | E44: =E35+E42 | F44: =F35+F42 | G44: =G35+G42 | H44: =H35+H42 | I44: =I35+I42
A46: ▌ 资产负债表平衡校验
B47: =IF(ABS(B19-B44)<1,"✓ 平衡","✗ 不平衡") | C47: =IF(ABS(C19-C44)<1,"✓ 平衡","✗ 不平衡") | D47: =IF(ABS(D19-D44)<1,"✓ 平衡","✗ 不平衡") | E47: =IF(ABS(E19-E44)<1,"✓ 平衡","✗ 不平衡") | F47: =IF(ABS(F19-F44)<1,"✓ 平衡","✗ 不平衡") | G47: =IF(ABS(G19-G44)<1,"✓ 平衡","✗ 不平衡") | H47: =IF(ABS(H19-H44)<1,"✓ 平衡","✗ 不平衡") | I47: =IF(ABS(I19-I44)<1,"✓ 平衡","✗ 不平衡")

Sheet 情景分析
A1: 星座能源公司（CEG）—— 情景分析（2026E–2029E）
A2: 三大情景覆盖AI需求爆发程度、卡尔派恩整合进度及电力市场价格假设差异
A4: 关键假设 | B4: 乐观情景 (Bull) | C4: 基准情景 (Base) | D4: 悲观情景 (Bear)
A5: ── 宏观与市场假设 ──
A6: 2026E收入（百万美元） | B6: $38,200 | C6: $34,400 | D6: $31,500
A7: 2029E收入（百万美元） | B7: $47,500 | C7: $40,500 | D7: $34,800
A8: 2026–29E收入CAGR | B8: 11.4% | C8: 5.6% | D8: 3.4%
A9: 2029E EBITDA利润率 | B9: 32.0% | C9: 28.5% | D9: 24.0%
A10: 2029E EBITDA（百万美元） | B10: $15,200 | C10: $11,543 | D10: $8,352
A12: ── 核能与发电假设 ──
A13: 2029E核能发电量（TWh） | B13: 198 | C13: 192 | D13: 184
A14: 2029E核能实现价格（$/MWh） | B14: $68.00 | C14: $62.00 | D14: $54.00
A15: 核电功率提升规模（MW） | B15: 1,200 | C15: 1,000 | D15: 600
A16: 卡尔派恩协同效益（百万美元，2026E） | B16: $450 | C16: $300 | D16: $150
A18: ── AI/数据中心PPA假设 ──
A19: 新签PPA（累计MW，2026–29E） | B19: 8,000+ | C19: 5,650 | D19: 3,000
A20: PPA平均溢价（vs.现货市场） | B20: +35% | C20: +25% | D20: +10%
A22: ── 估值假设 ──
A23: 目标EV/EBITDA倍数 | B23: 18.0x | C23: 15.0x | D23: 11.0x
A24: 目标P/E倍数（2027E EPS） | B24: 22.0x | C24: 18.0x | D24: 13.0x
A25: WACC | B25: 7.5% | C25: 7.975% | D25: 9.0%
A26: 永续增长率（g） | B26: 3.5% | C26: 3.0% | D26: 2.0%
A28: ── 估值结果 ──
A29: 目标股价（美元） | B29: $340 | C29: $255 | D29: $170
A30: 较当前股价的涨跌幅（基于$220基准价） | B30: +55% | C30: +16% | D30: -23%
A32: ── 股东回报假设 ──
A33: 2026E年化股息（美元/股） | B33: $1.92 | C33: $1.76 | D33: $1.60
A34: 2026–29E累计股票回购（百万美元） | B34: $3,500 | C34: $2,600 | D34: $1,500

Sheet DCF估值假设
A1: 星座能源公司（CEG）—— DCF估值假设（基准情景）
A2: （预测期：2026E–2029E，终值法：戈登增长模型 + EV/EBITDA双验证）
A4: ▌ WACC计算
A5: 无风险利率（10年期美国国债） | B5: 0.044 | C5: 4.40% | D5: 当前市场水平
A6: 市场风险溢价（ERP） | B6: 0.055 | C6: 5.50% | D6: Damodaran美国ERP
A7: Beta值（调整后） | B7: 0.65 | C7: 0.65 | D7: 彭博调整后5年周Beta
A8: 权益成本（Ke = Rf + β×ERP） | B8: =B5+B7*B6 | C8: ~7.975% | D8: 自动计算
A9: 税前债务成本（Kd） | B9: 0.048 | C9: 4.80% | D9: 基于当前发债利率
A10: 边际税率 | B10: 0.21 | C10: 21.0% | D10: 公司有效税率
A11: 税后债务成本（Kd×(1-t)） | B11: =B9*(1-B10) | C11: ~3.79% | D11: 自动计算
A12: 权益比例（E/V） | B12: 0.58 | C12: 58% | D12: 基于目标资本结构
A13: 债务比例（D/V） | B13: =1-B12 | C13: 42% | D13: 自动计算
A14: WACC = Ke×E/V + Kd(1-t)×D/V | B14: =B8*B12+B11*B13 | C14: ~7.975% | D14: 核心折现率
A16: ▌ 终值假设
A17: 永续增长率（g） | B17: 0.03 | C17: 3.00% | D17: 略低于名义GDP预期
A18: 终值年（最后预测年度） | B18: 2029 | C18: 2029年 | D18: 预测期最后一年
A19: 方法一：戈登增长模型（GGM）
A20: 终年EBITDA（百万美元） | B20: 11543 | C20: $11,543M | D20: 来自利润表模型
A21: → 终值 = EBITDA×(1+g)/(WACC-g) | B21: =B20*(1+B17)/(B14-B17) | C21: ~$235,367M | D21: 自动计算
A22: 方法二：退出EV/EBITDA倍数
A23: 退出EV/EBITDA倍数（基准） | B23: 15 | C23: 15.0x | D23: 参考同业中枢
A24: → 终值 = 终年EBITDA × 倍数 | B24: =B20*B23 | C24: ~$173,145M | D24: 自动计算
A25: 终值权重（GGM : EV/EBITDA） | B25: 50%/50% | C25: 各取50% | D25: 双方法均权
A26: 加权平均终值 | B26: =(B21+B24)/2 | C26: ~$204,256M | D26: 自动计算
A28: ▌ 估值结果摘要（基准情景）
A29: 企业价值（EV，百万美元） | B29: ~$262,000M | C29: 折现预测期FCF + 折现终值
A30: 减：净债务（百万美元） | B30: ~$(19,800)M | C30: 长期债务 - 现金及等价物
A31: 减：核退役义务（ARO，百万美元） | B31: ~$(4,200)M | C31: 资产退役义务现值
A32: 权益价值（百万美元） | B32: ~$238,000M | C32: EV - 净债务 - ARO
A33: 稀释股数（百万股） | B33: ~314M | C33: 2026E加权平均摊薄股数
A34: 隐含目标股价（美元） | B34: ~$255 | C34: 权益价值 / 稀释股数
A35: 相对当前股价涨跌幅 | B35: +16% vs. $220基准 | C35: 12个月目标价
A37: 目标EV/EBITDA（2026E） | B37: ~15.0x | C37: 行业合理估值中枢
A38: 目标P/E（2027E EPS，$13.20） | B38: ~19.3x | C38: 成长型公用事业合理溢价
